README.rst
setup.cfg
setup.py
crowdastro/__init__.py
crowdastro/__main__.py
crowdastro/_catalogue.py
crowdastro/_plot_classifier.py
crowdastro/_show_classifier_subject.py
crowdastro/checksums.py
crowdastro/classifier.py
crowdastro/compile_cnn.py
crowdastro/config.py
crowdastro/consensuses.py
crowdastro/crowdastro.json
crowdastro/elais_labels.py
crowdastro/exceptions.py
crowdastro/generate_annotator_labels.py
crowdastro/generate_cnn_outputs.py
crowdastro/generate_dataset.py
crowdastro/generate_test_sets.py
crowdastro/generate_training_data.py
crowdastro/import_data.py
crowdastro/plot.py
crowdastro/repack_h5.py
crowdastro/rgz_data.py
crowdastro/rgz_show.py
crowdastro/rgzatlascat.py
crowdastro/show_filters.py
crowdastro/test.py
crowdastro/train.py
crowdastro/train_classifier.py
crowdastro/train_cnn.py
crowdastro.egg-info/PKG-INFO
crowdastro.egg-info/SOURCES.txt
crowdastro.egg-info/dependency_links.txt
crowdastro.egg-info/entry_points.txt
crowdastro.egg-info/requires.txt
crowdastro.egg-info/top_level.txt
crowdastro/../README.rst