Metadata-Version: 1.1
Name: crowdastro
Version: 0.1.1
Summary: Automated cross-identification of radio objects and host galaxies using crowdsourced labels from the Radio Galaxy Zoo.
Home-page: https://github.com/chengsoonong/crowdastro
Author: Matthew Alger
Author-email: matthew.alger@anu.edu.au
License: MIT
Keywords: machine-learning radio astronomy classification
Platform: UNKNOWN
Classifier: Development Status :: 3 - Alpha
Classifier: Intended Audience :: Science/Research
Classifier: Topic :: Scientific/Engineering :: Astronomy
Classifier: License :: OSI Approved :: MIT License
Classifier: Programming Language :: Python :: 3
Classifier: Programming Language :: Python :: 3.4
Classifier: Programming Language :: Python :: 3.5
